stockholm_data_manager/__init__.py
stockholm_data_manager/constants.py
stockholm_data_manager/core/__init__.py
stockholm_data_manager/plugins/__init__.py
stockholm_data_manager/plugins/json2sheets.py
stockholm_data_manager/sterile/__init__.py
stockholm_data_manager/sterile/gsprd.py
stockholm_data_manager/sterile/time.py
stockholm_data_manager/utils/__init__.py
stockholm_data_manager/utils/logger.py
stockholm_data_manager/utils/train_test_split.py
stockholm_data_manager-0.14.1.dist-info/WHEEL
stockholm_data_manager-0.14.1.dist-info/METADATA
stockholm_data_manager-0.14.1.dist-info/RECORD
