Metadata-Version: 2.1
Name: stockholm-data-manager
Version: 0.14.1
Summary: Stockholm dataset manager.
Author: Amresh Venugopal
Author-email: amresh.venugopal@gmail.com
Requires-Python: >=3.6,<4.0
Classifier: Programming Language :: Python :: 3
Classifier: Programming Language :: Python :: 3.6
Classifier: Programming Language :: Python :: 3.7
Classifier: Programming Language :: Python :: 3.8
Requires-Dist: coloredlogs (>=15.0,<16.0)
Requires-Dist: gspread (>=3.6.0,<4.0.0)
Requires-Dist: tqdm (>=4.50.2,<5.0.0)
